fast_kinematics.cpython-310-x86_64-linux-gnu.so
fast_kinematics-0.2.2.dist-info/top_level.txt
fast_kinematics-0.2.2.dist-info/RECORD
fast_kinematics-0.2.2.dist-info/METADATA
fast_kinematics-0.2.2.dist-info/WHEEL
