Metadata-Version: 2.1
Name: fast_kinematics
Version: 0.2.2
Summary: A fast kinematics library for robotics
Home-page: https://github.com/Lexseal/fast_kinematics
Author: Xinsong Lin
Author-email: x8lin@ucsd.edu
License: MIT
Requires: pytorch
Requires: numpy
Requires-Python: >=3.8
